pywebaudioplayer.py
pywebaudioplayer/__init__.py
pywebaudioplayer/core.py
pywebaudioplayer/jupyter.py
pywebaudioplayer/notebook.py
pywebaudioplayer/trackswitch.js/css/trackswitch.css
pywebaudioplayer/trackswitch.js/js/trackswitch.js
pywebaudioplayer/waveform-playlist/dist/waveform-playlist/css/main.css
pywebaudioplayer/waveform-playlist/dist/waveform-playlist/js/waveform-playlist.var.js
pywebaudioplayer/wavesurfer.js/src/wavesurfer.js
pywebaudioplayer-0.0.5.dist-info/LICENSE
pywebaudioplayer-0.0.5.dist-info/METADATA
pywebaudioplayer-0.0.5.dist-info/WHEEL
pywebaudioplayer-0.0.5.dist-info/top_level.txt
pywebaudioplayer-0.0.5.dist-info/RECORD
